AUTHORS.rst
CONTRIBUTING.rst
HISTORY.rst
LICENSE
MANIFEST.in
README.rst
setup.cfg
setup.py
docs/Makefile
docs/authors.rst
docs/conf.py
docs/contributing.rst
docs/history.rst
docs/index.rst
docs/installation.rst
docs/make.bat
docs/readme.rst
docs/usage.rst
pyinfoepub/__init__.py
pyinfoepub/infoepub.py
pyinfoepub/pyinfoepub.py
pyinfoepub.egg-info/PKG-INFO
pyinfoepub.egg-info/SOURCES.txt
pyinfoepub.egg-info/dependency_links.txt
pyinfoepub.egg-info/not-zip-safe
pyinfoepub.egg-info/top_level.txt
pyinfoepub/parsers/__init__.py
pyinfoepub/parsers/parsers_epub.py
pyinfoepub/templates/__init__.py
pyinfoepub/templates/cli.py
tests/.coverage
tests/__init__.py
tests/runtests.py
tests/test_info_epub.py
tests/test_parsers.py
tests/test_template_cli.py
tests/samples/Franz Kafka - Metamorphosis.epub
tests/samples/README.txt
tests/samples/content.opf
tests/samples/toc.ncx