Metadata-Version: 1.1
Name: pyinfoepub
Version: 0.2
Summary: PyInfoEpub helps you retrieve specific information from an epub file.
Home-page: https://github.com/cristianav/PyInfoEpub
Author: Cristian Năvălici
Author-email: cristian.navalici@gmail.com
License: GPLv3
Keywords: pyinfoepub
Platform: UNKNOWN
Classifier: Development Status :: 4 - Beta
Classifier: Intended Audience :: Developers
Classifier: Intended Audience :: Education
Classifier: Intended Audience :: End Users/Desktop
Classifier: License :: OSI Approved :: GNU General Public License v3 (GPLv3)
Classifier: Natural Language :: English
Classifier: Programming Language :: Python :: 3
Classifier: Programming Language :: Python :: 3.3
Classifier: Programming Language :: Python :: 3.4
